<Achievement active="1" id="2602" kind="kills" MS_side="0" amount="10000" tags="weapons_R">
	<UI name="@ar03Kill25" desc="@ar03Kill25_desc"/>
	<Filters>
		<Filter kind="enemy" param="1"/>
		<Filter kind="weapon" param="ar03_shop"/>
		<Filter kind="weapon" param="ar03_bundle_shop"/>
		<Filter kind="claymore" param="0"/>
		<Filter kind="grenade" param="0"/>
		<Filter kind="kill_zone" param="0"/>
		<Filter kind="explosion" param="0"/>
	</Filters>
	<BannerImage image="challenge_strip_weapon25_03" type="stripe"/>
</Achievement>
