<Achievement active="1" id="96" kind="kills" MS_side="0" amount="250">
	<UI name="@hammerSickleKills" desc="@hammerSickleKills_desc"/>
	<Filters>
		<Filter kind="enemy" param="1"/>
		<Filter kind="player" param="1"/>			
		<Filter kind="weapon" param="kn41_ww2"/>
		<Filter kind="weapon" param="kn42_ww2"/>
		<Filter kind="weapon" param="kn42_viet"/>
		<Filter kind="claymore" param="0"/>
		<Filter kind="grenade" param="0"/>
		<Filter kind="kill_zone" param="0"/>
		<Filter kind="explosion" param="0"/>
	</Filters>		
	<BannerImage image="challenge_mark_ww2" type="mark" />		
</Achievement>
